Package_api/__init__.py
Package_api/json.py
Package_api/oops.py
anirudh_globalmart_api-0.2.dist-info/METADATA
anirudh_globalmart_api-0.2.dist-info/WHEEL
anirudh_globalmart_api-0.2.dist-info/license.txt
anirudh_globalmart_api-0.2.dist-info/top_level.txt
anirudh_globalmart_api-0.2.dist-info/RECORD
