Metadata-Version: 2.1
Name: anirudh-globalmart-api
Version: 0.2
Summary: API package that provides us the method to fetch the data from the API, along with the method to convert that into proper dataframe
Author: Anirudh
Author-email: anirudhsrinivas@gmail.com
License: MIT
License-File: license.txt
Requires-Dist: pandas
Requires-Dist: requests
